infeready/__init__.py
infeready/infeready.py
infeready/sources/__init__.py
infeready/sources/langchain_docs.py
infeready-0.0.1.dist-info/LICENSE
infeready-0.0.1.dist-info/METADATA
infeready-0.0.1.dist-info/WHEEL
infeready-0.0.1.dist-info/RECORD
