Metadata-Version: 2.1
Name: infeready
Version: 0.0.1
Summary: Inferready helps you combine all the components of your prompt into a single LLM-ready payload
Author: Alex Mavrogiannis
Author-email: almavrog@gmail.com
Requires-Python: >=3.9,<4.0
Classifier: Programming Language :: Python :: 3
Classifier: Programming Language :: Python :: 3.9
Classifier: Programming Language :: Python :: 3.10
Classifier: Programming Language :: Python :: 3.11
Classifier: Programming Language :: Python :: 3.12
Requires-Dist: jinja2 (>=3.1.3,<4.0.0)
Requires-Dist: langchain (>=0.1.12,<0.2.0)
Requires-Dist: pytest (>=8.1.1,<9.0.0)
